{
  "coc.preferences.formatOnSaveFiletypes": [
    "*"
  ],
  "languageserver": {
    "go": {
      "command": "gopls",
      "filetypes": [
        "go"
      ],
      "rootPatterns": [
        "go.mod",
        ".git",
        ".vim"
      ]
    },
    "terraform": {
      "args": [
        "serve"
      ],
      "command": "terraform-ls",
      "filetypes": [
        "terraform",
        "tf"
      ],
      "initializationOptions": {},
      "settings": {}
    }
  },
  "suggest.autoTrigger": "none"
}
