{
  "entries": {
    "tap": {
      "homebrew/core": {
        "revision": "84343001e0a5f4fbd601c67d2dc38abdadb3000f"
      },
      "homebrew/bundle": {
        "revision": "6d2f307b918355df929b94b4cf5507603e802a21"
      },
      "homebrew/cask": {
        "revision": "959836865f73a4a8e21e6aaee1ffb4db5f27c19f"
      }
    },
    "brew": {
      "bat": {
        "version": "0.12.1",
        "bottle": {
          "cellar": ":any_skip_relocation",
          "prefix": "/usr/local",
          "files": {
            "catalina": {
              "url": "https://homebrew.bintray.com/bottles/bat-0.12.1.catalina.bottle.2.tar.gz",
              "sha256": "fe47d61a6eedc6442d4a2b45bb15eadce806102c46247dd866e762fc510f2ac0"
            },
            "mojave": {
              "url": "https://homebrew.bintray.com/bottles/bat-0.12.1.mojave.bottle.2.tar.gz",
              "sha256": "c01694ccd70256fe852f5f597ed1ab917161642e1309b367caa537f77f98ebf8"
            },
            "high_sierra": {
              "url": "https://homebrew.bintray.com/bottles/bat-0.12.1.high_sierra.bottle.2.tar.gz",
              "sha256": "d06770fb4f496a0dfa8294431d65d93c53c4fa14a09c28ca7d87bbacf8419cb3"
            }
          }
        }
      },
      "cmake": {
        "version": "3.16.3",
        "bottle": {
          "cellar": ":any_skip_relocation",
          "prefix": "/usr/local",
          "files": {
            "catalina": {
              "url": "https://homebrew.bintray.com/bottles/cmake-3.16.3.catalina.bottle.tar.gz",
              "sha256": "eb47fab78f567ef95be459336db2da86394e196ce544eee3cfdfa3fbb0861d2d"
            },
            "mojave": {
              "url": "https://homebrew.bintray.com/bottles/cmake-3.16.3.mojave.bottle.tar.gz",
              "sha256": "4244d5f4624f0d16d2a2259b63246ac8c6bb0cf06f84231e65b4b6400a28bc42"
            },
            "high_sierra": {
              "url": "https://homebrew.bintray.com/bottles/cmake-3.16.3.high_sierra.bottle.tar.gz",
              "sha256": "7e3d416144b1962929b9f71ed469356b885ee827dd4216bbc78190a897bf6316"
            }
          }
        }
      },
      "direnv": {
        "version": "2.21.2",
        "bottle": {
          "cellar": ":any_skip_relocation",
          "prefix": "/usr/local",
          "files": {
            "catalina": {
              "url": "https://homebrew.bintray.com/bottles/direnv-2.21.2.catalina.bottle.tar.gz",
              "sha256": "31a7b6b1f16dd3e881ec693cb83e07757500f8d4810a5ebad3ab5986f7a6ef28"
            },
            "mojave": {
              "url": "https://homebrew.bintray.com/bottles/direnv-2.21.2.mojave.bottle.tar.gz",
              "sha256": "6a79378f41555b964e95c093c4a693fd2252c873bae453ebb309ec148eaeac7b"
            },
            "high_sierra": {
              "url": "https://homebrew.bintray.com/bottles/direnv-2.21.2.high_sierra.bottle.tar.gz",
              "sha256": "e490c0f7a242c35343e2f4d108b069380a9f73b2c7656d23db1c8940e549920b"
            }
          }
        }
      },
      "fzf": {
        "version": "0.20.0",
        "bottle": {
          "cellar": ":any_skip_relocation",
          "prefix": "/usr/local",
          "files": {
            "catalina": {
              "url": "https://homebrew.bintray.com/bottles/fzf-0.20.0.catalina.bottle.tar.gz",
              "sha256": "0d51962d904b7cd680fd316cc4691b5a562ce1ae77d4dcbfd40006f91c0945d6"
            },
            "mojave": {
              "url": "https://homebrew.bintray.com/bottles/fzf-0.20.0.mojave.bottle.tar.gz",
              "sha256": "c523ba3a6266bb58697e27f45adbf1a01d13560c22a0302dc946d3277da53274"
            },
            "high_sierra": {
              "url": "https://homebrew.bintray.com/bottles/fzf-0.20.0.high_sierra.bottle.tar.gz",
              "sha256": "72b692bd10dcc27504657f6eaf40d60f60c290f2b13052d6e6ad08ecc65f9c48"
            }
          }
        }
      },
      "ghq": {
        "version": "1.1.0",
        "bottle": {
          "cellar": ":any_skip_relocation",
          "prefix": "/usr/local",
          "files": {
            "catalina": {
              "url": "https://homebrew.bintray.com/bottles/ghq-1.1.0.catalina.bottle.tar.gz",
              "sha256": "094a5d328a580acd73d1d7759a45170648a03870521e229f36e01c3ce3f0fae8"
            },
            "mojave": {
              "url": "https://homebrew.bintray.com/bottles/ghq-1.1.0.mojave.bottle.tar.gz",
              "sha256": "8a92b1559028e62b2adf94031343effb73fc1adf796e117323c2be8942c4c626"
            },
            "high_sierra": {
              "url": "https://homebrew.bintray.com/bottles/ghq-1.1.0.high_sierra.bottle.tar.gz",
              "sha256": "a329280f22f251831749b1cb38c8eff4645fa2bbf81e2488254981736593bb16"
            }
          }
        }
      },
      "graphviz": {
        "version": "2.42.2",
        "bottle": {
          "cellar": "/usr/local/Cellar",
          "prefix": "/usr/local",
          "files": {
            "catalina": {
              "url": "https://homebrew.bintray.com/bottles/graphviz-2.42.2.catalina.bottle.tar.gz",
              "sha256": "fd65173d4f2bf9b4412f42939acc10815ba8974f5cdac342a9afd619acc70829"
            },
            "mojave": {
              "url": "https://homebrew.bintray.com/bottles/graphviz-2.42.2.mojave.bottle.tar.gz",
              "sha256": "abf938b188d15e2bf1b7447635f1e13a46baaa00f0e38ea6e5122e603f6b491d"
            },
            "high_sierra": {
              "url": "https://homebrew.bintray.com/bottles/graphviz-2.42.2.high_sierra.bottle.tar.gz",
              "sha256": "df7bafeabe8c94cc513c394ba3fa587ae2b209a25fa42f1b507dfae67029f47d"
            }
          }
        }
      },
      "jq": {
        "version": "1.6",
        "bottle": {
          "cellar": ":any",
          "prefix": "/usr/local",
          "files": {
            "catalina": {
              "url": "https://homebrew.bintray.com/bottles/jq-1.6.catalina.bottle.1.tar.gz",
              "sha256": "820a3c85fcbb63088b160c7edf125d7e55fc2c5c1d51569304499c9cc4b89ce8"
            },
            "mojave": {
              "url": "https://homebrew.bintray.com/bottles/jq-1.6.mojave.bottle.1.tar.gz",
              "sha256": "71f0e76c5b22e5088426c971d5e795fe67abee7af6c2c4ae0cf4c0eb98ed21ff"
            },
            "high_sierra": {
              "url": "https://homebrew.bintray.com/bottles/jq-1.6.high_sierra.bottle.1.tar.gz",
              "sha256": "dffcffa4ea13e8f0f2b45c5121e529077e135ae9a47254c32182231662ee9b72"
            },
            "sierra": {
              "url": "https://homebrew.bintray.com/bottles/jq-1.6.sierra.bottle.1.tar.gz",
              "sha256": "bb4d19dc026c2d72c53eed78eaa0ab982e9fcad2cd2acc6d13e7a12ff658e877"
            }
          }
        }
      },
      "nkf": {
        "version": "2.1.5",
        "bottle": {
          "cellar": ":any_skip_relocation",
          "prefix": "/usr/local",
          "files": {
            "catalina": {
              "url": "https://homebrew.bintray.com/bottles/nkf-2.1.5.catalina.bottle.tar.gz",
              "sha256": "4a0694aedea8fcf96ecdfb6c60c0e14825591e7e7247e3944a00966d883398e6"
            },
            "mojave": {
              "url": "https://homebrew.bintray.com/bottles/nkf-2.1.5.mojave.bottle.tar.gz",
              "sha256": "85183c457daaecd9a3ce59cea556189ad0131c6134d77e7890643a3fb75e3965"
            },
            "high_sierra": {
              "url": "https://homebrew.bintray.com/bottles/nkf-2.1.5.high_sierra.bottle.tar.gz",
              "sha256": "9af47f293d4531c8d7ec5a81bd041349773f982b9710edca03eb3eb59b02a8b5"
            },
            "sierra": {
              "url": "https://homebrew.bintray.com/bottles/nkf-2.1.5.sierra.bottle.tar.gz",
              "sha256": "8d908ee97c34e85ed85c268c895e143d57c7afdd9bc232a75b690067281765fc"
            }
          }
        }
      },
      "pwgen": {
        "version": "2.08",
        "bottle": {
          "cellar": ":any_skip_relocation",
          "prefix": "/usr/local",
          "files": {
            "catalina": {
              "url": "https://homebrew.bintray.com/bottles/pwgen-2.08.catalina.bottle.tar.gz",
              "sha256": "725911d1fd71b259acb7b907c09ef86a03545afe95e161856130992fc0789ffc"
            },
            "mojave": {
              "url": "https://homebrew.bintray.com/bottles/pwgen-2.08.mojave.bottle.tar.gz",
              "sha256": "2f35a2d575e16a2ab0497cabfc927a7b40aba68edba574889bf9bbdf03572c12"
            },
            "high_sierra": {
              "url": "https://homebrew.bintray.com/bottles/pwgen-2.08.high_sierra.bottle.tar.gz",
              "sha256": "185f2f56eb03da60277520734452204ec2e0059cbc1f0af5d0fec1e7fa837658"
            },
            "sierra": {
              "url": "https://homebrew.bintray.com/bottles/pwgen-2.08.sierra.bottle.tar.gz",
              "sha256": "01a0709f74923e7b86d680f03d3ec056d3175cb7e54be176a26d5bfae890fd21"
            },
            "el_capitan": {
              "url": "https://homebrew.bintray.com/bottles/pwgen-2.08.el_capitan.bottle.tar.gz",
              "sha256": "7dade70b172cb91635afffe8bb1eadb251f9dbd3368ab9e4a37f98a7c0a14b01"
            },
            "yosemite": {
              "url": "https://homebrew.bintray.com/bottles/pwgen-2.08.yosemite.bottle.tar.gz",
              "sha256": "1799bdbb42974d10e2ff3a4e382351b1f03f0a3be31c15ff718d8935d1226101"
            }
          }
        }
      },
      "starship": {
        "version": "0.33.1",
        "bottle": {
          "cellar": ":any_skip_relocation",
          "prefix": "/usr/local",
          "files": {
            "catalina": {
              "url": "https://homebrew.bintray.com/bottles/starship-0.33.1.catalina.bottle.tar.gz",
              "sha256": "2fcf639cd449b211179f102b54e8f60293c1efaa9222a42e6a544f82e2929d61"
            },
            "mojave": {
              "url": "https://homebrew.bintray.com/bottles/starship-0.33.1.mojave.bottle.tar.gz",
              "sha256": "2b59dcbc3bdb37652f8d49bb648a8970c995bd4493979e3763619dbbe67d51ca"
            },
            "high_sierra": {
              "url": "https://homebrew.bintray.com/bottles/starship-0.33.1.high_sierra.bottle.tar.gz",
              "sha256": "0a650fb57fd0dbe002d11cba09d5ae254d6f3d78695ded147142a59a3d086b33"
            }
          }
        }
      },
      "tmux": {
        "version": "3.0a",
        "bottle": {
          "cellar": ":any",
          "prefix": "/usr/local",
          "files": {
            "catalina": {
              "url": "https://homebrew.bintray.com/bottles/tmux-3.0a.catalina.bottle.tar.gz",
              "sha256": "3d29caf7e2b87c9f1af575b4ec10af3e29c5de6979a8bd884153d9e8e1b69f20"
            },
            "mojave": {
              "url": "https://homebrew.bintray.com/bottles/tmux-3.0a.mojave.bottle.tar.gz",
              "sha256": "6cfd3987dcda2901a3ed423138db7782ea88a993e1409c4ebb9d647b1c007e8a"
            },
            "high_sierra": {
              "url": "https://homebrew.bintray.com/bottles/tmux-3.0a.high_sierra.bottle.tar.gz",
              "sha256": "c7c42853ca6a3a5ad6ab6544defee14e450643f5ace274b9cf00d348e8525993"
            }
          }
        }
      },
      "tree": {
        "version": "1.8.0",
        "bottle": {
          "cellar": ":any_skip_relocation",
          "prefix": "/usr/local",
          "files": {
            "catalina": {
              "url": "https://homebrew.bintray.com/bottles/tree-1.8.0.catalina.bottle.tar.gz",
              "sha256": "18f7984bdbab22251e9fc3c7832dbace5c7f7a77e8d63717bb0078385e2bf255"
            },
            "mojave": {
              "url": "https://homebrew.bintray.com/bottles/tree-1.8.0.mojave.bottle.tar.gz",
              "sha256": "7152288c457dd893de50fa9d6ac9a8599748564e1b3586eec8eff7057089051a"
            },
            "high_sierra": {
              "url": "https://homebrew.bintray.com/bottles/tree-1.8.0.high_sierra.bottle.tar.gz",
              "sha256": "107d965994381d34e90b58a62f1c306c1b8a698db2696cdd905ba65c801ecc3b"
            },
            "sierra": {
              "url": "https://homebrew.bintray.com/bottles/tree-1.8.0.sierra.bottle.tar.gz",
              "sha256": "07d980571469a0cc699c69a8726eee338f782ba61c041e58f01ddb2924d08aeb"
            }
          }
        }
      },
      "git": {
        "version": "2.25.0_1",
        "bottle": {
          "cellar": "/usr/local/Cellar",
          "prefix": "/usr/local",
          "files": {
            "catalina": {
              "url": "https://homebrew.bintray.com/bottles/git-2.25.0_1.catalina.bottle.tar.gz",
              "sha256": "9ab68a09b14009dd3c28fcd3e6ef98213f675887615cab5c67d62a026ccc019b"
            },
            "mojave": {
              "url": "https://homebrew.bintray.com/bottles/git-2.25.0_1.mojave.bottle.tar.gz",
              "sha256": "54508f6ad675b1a3964d8576b9123d1459f6edf4f8847e229b56ec76cf49014b"
            },
            "high_sierra": {
              "url": "https://homebrew.bintray.com/bottles/git-2.25.0_1.high_sierra.bottle.tar.gz",
              "sha256": "cac935cce4729d0cc61ce0b3cda18848d811c6e51a03498b6f44e6f3764b3b9e"
            }
          }
        }
      },
      "gibo": {
        "version": "2.2.3",
        "bottle": false
      },
      "tig": {
        "version": "2.5.0",
        "bottle": {
          "cellar": ":any",
          "prefix": "/usr/local",
          "files": {
            "catalina": {
              "url": "https://homebrew.bintray.com/bottles/tig-2.5.0.catalina.bottle.tar.gz",
              "sha256": "03f5fc99e3763dc90dd4e2a3445fb9e4a65a2db790b8aa40c1d56cd08d1d5f6f"
            },
            "mojave": {
              "url": "https://homebrew.bintray.com/bottles/tig-2.5.0.mojave.bottle.tar.gz",
              "sha256": "5fbd4ddf058724d51f88221bb54f949dd79941d7654f63881c62bf9768a7e12e"
            },
            "high_sierra": {
              "url": "https://homebrew.bintray.com/bottles/tig-2.5.0.high_sierra.bottle.tar.gz",
              "sha256": "8c85a68d1ff0400649e18b47160152ea1220e72afa6217d916462ecc7053bf14"
            }
          }
        }
      },
      "hub": {
        "version": "2.14.1",
        "bottle": {
          "cellar": ":any_skip_relocation",
          "prefix": "/usr/local",
          "files": {
            "catalina": {
              "url": "https://homebrew.bintray.com/bottles/hub-2.14.1.catalina.bottle.tar.gz",
              "sha256": "f092116bb42f4149b0a2abb25ee1752eec32923fe9bd0772607404b3da86e866"
            },
            "mojave": {
              "url": "https://homebrew.bintray.com/bottles/hub-2.14.1.mojave.bottle.tar.gz",
              "sha256": "671f391bbbd66507a7a9f871ee7222326eb54471478a2e5e1e6122cb58534425"
            },
            "high_sierra": {
              "url": "https://homebrew.bintray.com/bottles/hub-2.14.1.high_sierra.bottle.tar.gz",
              "sha256": "bb9269b14335df7a77cbe8072df072471c980b497c06f33b603744a60fc09d95"
            }
          }
        }
      },
      "git-secret": {
        "version": "0.3.2",
        "bottle": {
          "cellar": ":any_skip_relocation",
          "prefix": "/usr/local",
          "files": {
            "catalina": {
              "url": "https://homebrew.bintray.com/bottles/git-secret-0.3.2.catalina.bottle.tar.gz",
              "sha256": "2fb53e4162baa1e614c3d73dbb24257604cf8b7864f73deeba21c784c6434193"
            },
            "mojave": {
              "url": "https://homebrew.bintray.com/bottles/git-secret-0.3.2.mojave.bottle.tar.gz",
              "sha256": "2fb53e4162baa1e614c3d73dbb24257604cf8b7864f73deeba21c784c6434193"
            },
            "high_sierra": {
              "url": "https://homebrew.bintray.com/bottles/git-secret-0.3.2.high_sierra.bottle.tar.gz",
              "sha256": "2fb53e4162baa1e614c3d73dbb24257604cf8b7864f73deeba21c784c6434193"
            }
          }
        }
      },
      "awscli": {
        "version": "1.17.9",
        "bottle": {
          "cellar": ":any_skip_relocation",
          "prefix": "/usr/local",
          "files": {
            "catalina": {
              "url": "https://homebrew.bintray.com/bottles/awscli-1.17.9.catalina.bottle.tar.gz",
              "sha256": "37a440efce1df4fb81c021b231871cd9788046a3f17f83bc4254a2f15d4797ce"
            },
            "mojave": {
              "url": "https://homebrew.bintray.com/bottles/awscli-1.17.9.mojave.bottle.tar.gz",
              "sha256": "86fdc3092d701dcca89ef858b6db02e418d374ced3de7a8226b02f41559acb43"
            },
            "high_sierra": {
              "url": "https://homebrew.bintray.com/bottles/awscli-1.17.9.high_sierra.bottle.tar.gz",
              "sha256": "2b0d3bd2dadd77657686e96071f4187457ecb2d60cd43a6b2b601f1994b55105"
            }
          }
        }
      },
      "azure-cli": {
        "version": "2.0.80",
        "bottle": {
          "cellar": ":any",
          "prefix": "/usr/local",
          "files": {
            "catalina": {
              "url": "https://homebrew.bintray.com/bottles/azure-cli-2.0.80.catalina.bottle.tar.gz",
              "sha256": "e4eb4db187fc67bc3e77d5ddb153b898636e84b0c7a7bf5f66088d3e30436487"
            },
            "mojave": {
              "url": "https://homebrew.bintray.com/bottles/azure-cli-2.0.80.mojave.bottle.tar.gz",
              "sha256": "0287f144a62b81dfcd73e2ec2cd175e24190f778118481ef039a9850409b5f6f"
            },
            "high_sierra": {
              "url": "https://homebrew.bintray.com/bottles/azure-cli-2.0.80.high_sierra.bottle.tar.gz",
              "sha256": "7c517cb7c4acc5d9e0bbe2023b38bc6aa38437f78d71a5d8f257bec02d2397bd"
            }
          }
        }
      },
      "terraformer": {
        "version": "0.8.5",
        "bottle": {
          "cellar": ":any_skip_relocation",
          "prefix": "/usr/local",
          "files": {
            "catalina": {
              "url": "https://homebrew.bintray.com/bottles/terraformer-0.8.5.catalina.bottle.tar.gz",
              "sha256": "178deb67ec04ce1956e505ef2c03a8c443bb8bdeed698a7858f487b3a7a53e3b"
            },
            "mojave": {
              "url": "https://homebrew.bintray.com/bottles/terraformer-0.8.5.mojave.bottle.tar.gz",
              "sha256": "74d985028d26d8994debb214dbc17e0a7b51236daaaece0e5d23e2b4eac6c260"
            },
            "high_sierra": {
              "url": "https://homebrew.bintray.com/bottles/terraformer-0.8.5.high_sierra.bottle.tar.gz",
              "sha256": "e7b809c07e1c53f565cd686533c06a08db5e4c74cf938fd5bd9322ee89cd7403"
            }
          }
        }
      },
      "tfenv": {
        "version": "1.0.2",
        "bottle": false
      },
      "circleci": {
        "version": "0.1.5879",
        "bottle": {
          "cellar": ":any_skip_relocation",
          "prefix": "/usr/local",
          "files": {
            "catalina": {
              "url": "https://homebrew.bintray.com/bottles/circleci-0.1.5879.catalina.bottle.tar.gz",
              "sha256": "6c70e1810214aac26798cfc5ac8734fbecae1baee3af9af8b5f45dedca66d30c"
            },
            "mojave": {
              "url": "https://homebrew.bintray.com/bottles/circleci-0.1.5879.mojave.bottle.tar.gz",
              "sha256": "48adff67b7d69ed1a6656a754e754e8cae67ce4ec7929a805c405bbce89eabc9"
            },
            "high_sierra": {
              "url": "https://homebrew.bintray.com/bottles/circleci-0.1.5879.high_sierra.bottle.tar.gz",
              "sha256": "b82e42bd9c5026de007fbb5c684e8fd2875db82c25a935b9e22ff5563d94217f"
            },
            "sierra": {
              "url": "https://homebrew.bintray.com/bottles/circleci-0.1.5879.sierra.bottle.tar.gz",
              "sha256": "37088c6cc436902542b008a3f78aad369f7a199f0d24cb2b3573d0e95a795256"
            }
          }
        }
      },
      "go": {
        "version": "1.13.7",
        "bottle": {
          "cellar": "/usr/local/Cellar",
          "prefix": "/usr/local",
          "files": {
            "catalina": {
              "url": "https://homebrew.bintray.com/bottles/go-1.13.7.catalina.bottle.tar.gz",
              "sha256": "5ba18a71fa1ac99a0bc107389532b798d7fcaa61d88c6658a0c2fb0b53c37065"
            },
            "mojave": {
              "url": "https://homebrew.bintray.com/bottles/go-1.13.7.mojave.bottle.tar.gz",
              "sha256": "9cba4cf601c8ff2dde3152909e0394d827fb2dc16bf488f1a6a0701bf0366707"
            },
            "high_sierra": {
              "url": "https://homebrew.bintray.com/bottles/go-1.13.7.high_sierra.bottle.tar.gz",
              "sha256": "4f22d45ef315671c6d5fcdf853d3847997d92f13846ae1c289b469d4b50d8c13"
            }
          }
        }
      },
      "goenv": {
        "version": "1.23.3",
        "bottle": false
      },
      "node": {
        "version": "13.7.0",
        "bottle": {
          "cellar": ":any",
          "prefix": "/usr/local",
          "files": {
            "catalina": {
              "url": "https://homebrew.bintray.com/bottles/node-13.7.0.catalina.bottle.1.tar.gz",
              "sha256": "ba5bd9a80c8969a10df981521dde63fc8e2e2fdca97c0be7239d75cf9df80f92"
            },
            "mojave": {
              "url": "https://homebrew.bintray.com/bottles/node-13.7.0.mojave.bottle.1.tar.gz",
              "sha256": "634b52994ab2142281692f9c8796ca28d656aaab0f7f09f1a4f541ff5a2a03e5"
            },
            "high_sierra": {
              "url": "https://homebrew.bintray.com/bottles/node-13.7.0.high_sierra.bottle.1.tar.gz",
              "sha256": "c52fc849ecb2ca089edd47f6bf21907c088afd5d5c43baaa015c0a6fe9054af8"
            }
          }
        }
      },
      "elm": {
        "version": "0.19.1",
        "bottle": {
          "cellar": ":any_skip_relocation",
          "prefix": "/usr/local",
          "files": {
            "catalina": {
              "url": "https://homebrew.bintray.com/bottles/elm-0.19.1.catalina.bottle.tar.gz",
              "sha256": "e1bbfe4ff7deba3ed60eb55b81b86b6d3346325bea584802ca1212369f0fa0bb"
            },
            "mojave": {
              "url": "https://homebrew.bintray.com/bottles/elm-0.19.1.mojave.bottle.tar.gz",
              "sha256": "288eeb47caccfaa9bae220492cee8de7206d40b7760e1e309a139a2398f9710d"
            },
            "high_sierra": {
              "url": "https://homebrew.bintray.com/bottles/elm-0.19.1.high_sierra.bottle.tar.gz",
              "sha256": "7fb65ff925701c39bbc7d9a5099cd88f10a56949ae019bc8817035ed1d56edbd"
            }
          }
        }
      },
      "rustup-init": {
        "version": "1.21.1",
        "bottle": {
          "cellar": ":any_skip_relocation",
          "prefix": "/usr/local",
          "files": {
            "catalina": {
              "url": "https://homebrew.bintray.com/bottles/rustup-init-1.21.1.catalina.bottle.tar.gz",
              "sha256": "a97694534834b8c87660c7d3ecf0cad6f030c39c50cd365c6a28ac167aaa4464"
            },
            "mojave": {
              "url": "https://homebrew.bintray.com/bottles/rustup-init-1.21.1.mojave.bottle.tar.gz",
              "sha256": "fad5c12bfcd7223aa445718df1427315fcc466df93c4c33f0629ecdf146191c8"
            },
            "high_sierra": {
              "url": "https://homebrew.bintray.com/bottles/rustup-init-1.21.1.high_sierra.bottle.tar.gz",
              "sha256": "6b52ab63b32993cfbcc9f5a2329b62c22501fbf9c4cb3b797b34d20d9641204d"
            }
          }
        }
      },
      "protobuf": {
        "version": "3.11.2",
        "bottle": {
          "cellar": ":any",
          "prefix": "/usr/local",
          "files": {
            "catalina": {
              "url": "https://homebrew.bintray.com/bottles/protobuf-3.11.2.catalina.bottle.tar.gz",
              "sha256": "3fdda0c68757e397a80cf6d87ffb1f6570f459c368a1288c316e932687c5a98f"
            },
            "mojave": {
              "url": "https://homebrew.bintray.com/bottles/protobuf-3.11.2.mojave.bottle.tar.gz",
              "sha256": "c2c8d923c866867eec44813a8264684bd6deb5fc98fc0ca257eaf1dea34ba183"
            },
            "high_sierra": {
              "url": "https://homebrew.bintray.com/bottles/protobuf-3.11.2.high_sierra.bottle.tar.gz",
              "sha256": "a772a6c0dc4a95ae6a2cc200664995ef2749d08da8e0965c9b18e932cd5ff19c"
            }
          }
        }
      },
      "shellcheck": {
        "version": "0.7.0",
        "bottle": {
          "cellar": ":any_skip_relocation",
          "prefix": "/usr/local",
          "files": {
            "mojave": {
              "url": "https://homebrew.bintray.com/bottles/shellcheck-0.7.0.mojave.bottle.tar.gz",
              "sha256": "be8e084d55379a4b5a8bfba78ad298f966f0888e6c3eb7e5202527d3938f3501"
            },
            "high_sierra": {
              "url": "https://homebrew.bintray.com/bottles/shellcheck-0.7.0.high_sierra.bottle.tar.gz",
              "sha256": "a4e12db223139c82649fdc16a2d04184cbaf5fc413c1135b0a1100a16e33290b"
            },
            "sierra": {
              "url": "https://homebrew.bintray.com/bottles/shellcheck-0.7.0.sierra.bottle.tar.gz",
              "sha256": "770a22a491ae6316f7b6e56d8039d30693d857336ccc608de865750798480899"
            }
          }
        }
      },
      "vegeta": {
        "version": "12.7.0",
        "bottle": {
          "cellar": ":any_skip_relocation",
          "prefix": "/usr/local",
          "files": {
            "catalina": {
              "url": "https://homebrew.bintray.com/bottles/vegeta-12.7.0.catalina.bottle.tar.gz",
              "sha256": "8bcc25e5a17aabc111d71ea916e8433589a9fe9e41bf5f172c77faafdd4285c5"
            },
            "mojave": {
              "url": "https://homebrew.bintray.com/bottles/vegeta-12.7.0.mojave.bottle.tar.gz",
              "sha256": "5b40fdc60f3bb98cb1c922ecbf84ea48748e97a3e31d979378f1abc2b6ea032a"
            },
            "high_sierra": {
              "url": "https://homebrew.bintray.com/bottles/vegeta-12.7.0.high_sierra.bottle.tar.gz",
              "sha256": "d72fb9d6d2b987f0f35c0545d806a1ea4626e266641e6e8abecc4ce0be54e4ce"
            },
            "sierra": {
              "url": "https://homebrew.bintray.com/bottles/vegeta-12.7.0.sierra.bottle.tar.gz",
              "sha256": "1596ae7a805382e2073fbc92a94c105d4176d75aace961e829c00dedd47b97b9"
            }
          }
        }
      },
      "golangci/tap/golangci-lint": null,
      "kind": {
        "version": "0.7.0",
        "bottle": {
          "cellar": ":any_skip_relocation",
          "prefix": "/usr/local",
          "files": {
            "catalina": {
              "url": "https://homebrew.bintray.com/bottles/kind-0.7.0.catalina.bottle.tar.gz",
              "sha256": "fa2ba3846ebbb34f23bddeb09e646e9c25ce1db629b4e6edf40d7bd9d191f9d2"
            },
            "mojave": {
              "url": "https://homebrew.bintray.com/bottles/kind-0.7.0.mojave.bottle.tar.gz",
              "sha256": "a8aa767a31255c10b5b93890cfac3eb005b480b6b40220831f1dc235f0d8dea8"
            },
            "high_sierra": {
              "url": "https://homebrew.bintray.com/bottles/kind-0.7.0.high_sierra.bottle.tar.gz",
              "sha256": "12a4e4fdac5204ff6ea47cbcfb16722ba0671aaf1e97a14facd638ec437425ca"
            }
          }
        }
      },
      "kubernetes-cli": {
        "version": "1.17.2",
        "bottle": {
          "cellar": ":any_skip_relocation",
          "prefix": "/usr/local",
          "files": {
            "catalina": {
              "url": "https://homebrew.bintray.com/bottles/kubernetes-cli-1.17.2.catalina.bottle.tar.gz",
              "sha256": "6d17df661d41decb333b2565d80339600b912c4912921e694ccd11c52e80cbbe"
            },
            "mojave": {
              "url": "https://homebrew.bintray.com/bottles/kubernetes-cli-1.17.2.mojave.bottle.tar.gz",
              "sha256": "c2984f440358d79b01deddf8a5c350ccfb39e286113830203edeacfd014cd626"
            },
            "high_sierra": {
              "url": "https://homebrew.bintray.com/bottles/kubernetes-cli-1.17.2.high_sierra.bottle.tar.gz",
              "sha256": "15b3b57388694a7c80f6902ce0e3fbdc5f575d015de6b8c441bc3a4c6b1bc369"
            }
          }
        }
      },
      "kustomize": {
        "version": "3.5.4",
        "bottle": {
          "cellar": ":any_skip_relocation",
          "prefix": "/usr/local",
          "files": {
            "catalina": {
              "url": "https://homebrew.bintray.com/bottles/kustomize-3.5.4.catalina.bottle.1.tar.gz",
              "sha256": "e7e4728e65df26734f4815f517940b47d5a1d3cf6e0ce709772a76da4905c053"
            },
            "mojave": {
              "url": "https://homebrew.bintray.com/bottles/kustomize-3.5.4.mojave.bottle.1.tar.gz",
              "sha256": "ae5b7fa548e13b5d191ef95499b50a469ca29b840b086848d608bf9cc27c2e2f"
            },
            "high_sierra": {
              "url": "https://homebrew.bintray.com/bottles/kustomize-3.5.4.high_sierra.bottle.1.tar.gz",
              "sha256": "9cc7948af53b2711ef41d539032544ce472237c3466702bd5ac0d40370292148"
            }
          }
        }
      },
      "helm": {
        "version": "3.0.3",
        "bottle": {
          "cellar": ":any_skip_relocation",
          "prefix": "/usr/local",
          "files": {
            "catalina": {
              "url": "https://homebrew.bintray.com/bottles/helm-3.0.3.catalina.bottle.tar.gz",
              "sha256": "5987c80ea21063f3c26a799889ad3e0b35c73275bd3579e5a1f6785d6f3f43d5"
            },
            "mojave": {
              "url": "https://homebrew.bintray.com/bottles/helm-3.0.3.mojave.bottle.tar.gz",
              "sha256": "29239b6d467e3ebe810645e45a4635a5e239ee6f1e1bd33d7bfa33e02a79ceae"
            },
            "high_sierra": {
              "url": "https://homebrew.bintray.com/bottles/helm-3.0.3.high_sierra.bottle.tar.gz",
              "sha256": "dd5a05fa985c1a696a5b7db0aa7548e0de31094569558eabc2b2cdc4dac24264"
            }
          }
        }
      },
      "skaffold": {
        "version": "1.2.0",
        "bottle": {
          "cellar": ":any_skip_relocation",
          "prefix": "/usr/local",
          "files": {
            "catalina": {
              "url": "https://homebrew.bintray.com/bottles/skaffold-1.2.0.catalina.bottle.tar.gz",
              "sha256": "e09c836eaf50d27ed9118210b6d05007e16f21212518f0dfc9fabc76da38c81f"
            },
            "mojave": {
              "url": "https://homebrew.bintray.com/bottles/skaffold-1.2.0.mojave.bottle.tar.gz",
              "sha256": "31babe4ec12ae83d21d6cb933bd7ef36912851cd220ceb7d25c94cf510c1f62d"
            },
            "high_sierra": {
              "url": "https://homebrew.bintray.com/bottles/skaffold-1.2.0.high_sierra.bottle.tar.gz",
              "sha256": "e27916fc9c60b514f8efefa194998253955da864e9b974acf0737e92c7727ca5"
            }
          }
        }
      },
      "stern": {
        "version": "1.11.0",
        "bottle": {
          "cellar": ":any_skip_relocation",
          "prefix": "/usr/local",
          "files": {
            "catalina": {
              "url": "https://homebrew.bintray.com/bottles/stern-1.11.0.catalina.bottle.tar.gz",
              "sha256": "886c99c34ee64ae8ea2292822b268324b573449fb3d621b874c0746d071a5082"
            },
            "mojave": {
              "url": "https://homebrew.bintray.com/bottles/stern-1.11.0.mojave.bottle.tar.gz",
              "sha256": "f862bab034a7d05b995e762e7feae5d840db9099faba8465e4e20daa548f02f7"
            },
            "high_sierra": {
              "url": "https://homebrew.bintray.com/bottles/stern-1.11.0.high_sierra.bottle.tar.gz",
              "sha256": "fd68b5ceb1ef3a1cbdb51653530f0ac0625e59adb55b02c1b7dad2268db7e4b3"
            },
            "sierra": {
              "url": "https://homebrew.bintray.com/bottles/stern-1.11.0.sierra.bottle.tar.gz",
              "sha256": "01a7f817326d1172201d36df18cbee1ceca864d83e9cc528e301018b1510872f"
            }
          }
        }
      },
      "hadolint": {
        "version": "1.17.4",
        "bottle": {
          "cellar": ":any_skip_relocation",
          "prefix": "/usr/local",
          "files": {
            "catalina": {
              "url": "https://homebrew.bintray.com/bottles/hadolint-1.17.4.catalina.bottle.tar.gz",
              "sha256": "8188ae83745bef4a9d28d5d08faff1bf9c27522ba0cd2f55f77e8dbbcbebd5a2"
            },
            "mojave": {
              "url": "https://homebrew.bintray.com/bottles/hadolint-1.17.4.mojave.bottle.tar.gz",
              "sha256": "60a4ad1f6c0fd4514ab34bcbc0ed2187266958d604b12c6a4126494cbe633f95"
            },
            "high_sierra": {
              "url": "https://homebrew.bintray.com/bottles/hadolint-1.17.4.high_sierra.bottle.tar.gz",
              "sha256": "44ca2612d78903494068ee04720570f2575eaa163495b19913a8bfd22b078b40"
            }
          }
        }
      },
      "bash": {
        "version": "5.0.11",
        "bottle": {
          "cellar": "/usr/local/Cellar",
          "prefix": "/usr/local",
          "files": {
            "catalina": {
              "url": "https://homebrew.bintray.com/bottles/bash-5.0.11.catalina.bottle.tar.gz",
              "sha256": "c20c5b4c9864c58fd5347301bd8e8f78c4e0e8d3ba1ff109e200ff2612d30f11"
            },
            "mojave": {
              "url": "https://homebrew.bintray.com/bottles/bash-5.0.11.mojave.bottle.tar.gz",
              "sha256": "01d371ab4c7069858cbc660c18c8722dbc397a4fc85c66a5723d06c82a13e150"
            },
            "high_sierra": {
              "url": "https://homebrew.bintray.com/bottles/bash-5.0.11.high_sierra.bottle.tar.gz",
              "sha256": "d53c1b8ce452eef490b301a7afadaec97aa6942e4d921b0f39a46108edeb2a22"
            },
            "sierra": {
              "url": "https://homebrew.bintray.com/bottles/bash-5.0.11.sierra.bottle.tar.gz",
              "sha256": "0002727c12bd2d1fa059f5cd70045fd5b3bcbc654b82559429ac64fe37b41ac8"
            }
          }
        }
      },
      "gawk": {
        "version": "5.0.1",
        "bottle": {
          "cellar": "/usr/local/Cellar",
          "prefix": "/usr/local",
          "files": {
            "catalina": {
              "url": "https://homebrew.bintray.com/bottles/gawk-5.0.1.catalina.bottle.1.tar.gz",
              "sha256": "3bb22749e869048a14e444e738813ba883a719b757d641cf09dbc58ae3dde667"
            },
            "mojave": {
              "url": "https://homebrew.bintray.com/bottles/gawk-5.0.1.mojave.bottle.1.tar.gz",
              "sha256": "071ed9be337b30165c619cd6c5ef4204f047b81caaa860288a07d090c1a10d75"
            },
            "high_sierra": {
              "url": "https://homebrew.bintray.com/bottles/gawk-5.0.1.high_sierra.bottle.1.tar.gz",
              "sha256": "de2f0c453a79a87a9274b6ee71fa47c250783dad46573b168b5cbf71eb777d4f"
            }
          }
        }
      },
      "coreutils": {
        "version": "8.31",
        "bottle": {
          "cellar": "/usr/local/Cellar",
          "prefix": "/usr/local",
          "files": {
            "catalina": {
              "url": "https://homebrew.bintray.com/bottles/coreutils-8.31.catalina.bottle.1.tar.gz",
              "sha256": "7262e4c76483ea796454db828c25955be1e6b2bc8e056ba1dd6e92bfe1118da5"
            },
            "mojave": {
              "url": "https://homebrew.bintray.com/bottles/coreutils-8.31.mojave.bottle.1.tar.gz",
              "sha256": "05ae58c26a53c2dfa2d9d45943b9d21753eea59609f0a48caa59713d6f6392d7"
            },
            "high_sierra": {
              "url": "https://homebrew.bintray.com/bottles/coreutils-8.31.high_sierra.bottle.1.tar.gz",
              "sha256": "5cba7394f1995fad0f6215a7618f65983dcf84b93b076af18d09354051320fb2"
            }
          }
        }
      },
      "findutils": {
        "version": "4.7.0",
        "bottle": {
          "cellar": ":any_skip_relocation",
          "prefix": "/usr/local",
          "files": {
            "catalina": {
              "url": "https://homebrew.bintray.com/bottles/findutils-4.7.0.catalina.bottle.tar.gz",
              "sha256": "f9ba06f4d48275e8cab659450b05e77873e909f31104df450201a83d465ed1ca"
            },
            "mojave": {
              "url": "https://homebrew.bintray.com/bottles/findutils-4.7.0.mojave.bottle.tar.gz",
              "sha256": "3c609b729a1dc859459282a856ff6c164cd8388e531dad4e58c8d4c7acb670fb"
            },
            "high_sierra": {
              "url": "https://homebrew.bintray.com/bottles/findutils-4.7.0.high_sierra.bottle.tar.gz",
              "sha256": "996a9fe2b1829fdf7b7257bead0ef0c4315832e9ba21b149779abeb59dcbde30"
            },
            "sierra": {
              "url": "https://homebrew.bintray.com/bottles/findutils-4.7.0.sierra.bottle.tar.gz",
              "sha256": "4b66ce398f2d5f5c65bf0b05fcc55334398e75cb965a17d781d7c3a15a4bba61"
            }
          }
        }
      },
      "vim": {
        "version": "8.2.0150",
        "bottle": {
          "cellar": "/usr/local/Cellar",
          "prefix": "/usr/local",
          "files": {
            "catalina": {
              "url": "https://homebrew.bintray.com/bottles/vim-8.2.0150.catalina.bottle.tar.gz",
              "sha256": "0c132f82007b5eba0e26481a6c6d8b72d86008e8c0639e0c772da3ffe1c3a2a4"
            },
            "mojave": {
              "url": "https://homebrew.bintray.com/bottles/vim-8.2.0150.mojave.bottle.tar.gz",
              "sha256": "1075c70931571ddf64e208f47f4a2a99c6893a557bec1a9911a30c5ce1b20d7f"
            },
            "high_sierra": {
              "url": "https://homebrew.bintray.com/bottles/vim-8.2.0150.high_sierra.bottle.tar.gz",
              "sha256": "984f2f18d365f71ac5a9089b56552326444edee749be9fab0f401450d79bf8ec"
            }
          }
        }
      },
      "python": {
        "version": "3.7.6_1",
        "bottle": {
          "cellar": "/usr/local/Cellar",
          "prefix": "/usr/local",
          "files": {
            "catalina": {
              "url": "https://homebrew.bintray.com/bottles/python-3.7.6_1.catalina.bottle.tar.gz",
              "sha256": "3871ef8b53270576c46489ae397f245b84772c405085238790cf5faa1853b33a"
            },
            "mojave": {
              "url": "https://homebrew.bintray.com/bottles/python-3.7.6_1.mojave.bottle.tar.gz",
              "sha256": "643d627c2b4fc03a3286c397d299284ef8ce2d4a832737e41175f297d4f0862e"
            },
            "high_sierra": {
              "url": "https://homebrew.bintray.com/bottles/python-3.7.6_1.high_sierra.bottle.tar.gz",
              "sha256": "3504f29ae0366d08fc025cfe2885cd2e685f74ab041a341a393d3b6967f139d7"
            }
          }
        }
      },
      "pipenv": {
        "version": "2018.11.26_3",
        "bottle": {
          "cellar": ":any_skip_relocation",
          "prefix": "/usr/local",
          "files": {
            "catalina": {
              "url": "https://homebrew.bintray.com/bottles/pipenv-2018.11.26_3.catalina.bottle.tar.gz",
              "sha256": "db8a0ff25976267cfe7abc95a5a4660dc2e30ee7b96c447019c7ac53e4303300"
            },
            "mojave": {
              "url": "https://homebrew.bintray.com/bottles/pipenv-2018.11.26_3.mojave.bottle.tar.gz",
              "sha256": "b9cb743f74deb9a403e0c1a4cc9131658874035ae79c4a7462ad08a8f96bdad5"
            },
            "high_sierra": {
              "url": "https://homebrew.bintray.com/bottles/pipenv-2018.11.26_3.high_sierra.bottle.tar.gz",
              "sha256": "0c078b19e35de1e9834049a8c1836285a5a85b483ce8ffa90263c138e71f6161"
            }
          }
        }
      },
      "reattach-to-user-namespace": {
        "version": "2.8",
        "bottle": {
          "cellar": ":any_skip_relocation",
          "prefix": "/usr/local",
          "files": {
            "catalina": {
              "url": "https://homebrew.bintray.com/bottles/reattach-to-user-namespace-2.8.catalina.bottle.tar.gz",
              "sha256": "165edabd70a4acbdee2f3e09e9a37e9ca23b2d485ebe12d62511cef9c45fd757"
            },
            "mojave": {
              "url": "https://homebrew.bintray.com/bottles/reattach-to-user-namespace-2.8.mojave.bottle.tar.gz",
              "sha256": "388e45300bf6cf3888a490878c9a03b97c06a52fe316a18d099ab97bddbed295"
            },
            "high_sierra": {
              "url": "https://homebrew.bintray.com/bottles/reattach-to-user-namespace-2.8.high_sierra.bottle.tar.gz",
              "sha256": "adc59ad02ccf302e9c71c08d10a4eb95d5d210dbfebe9a00b41648b094c96f09"
            },
            "sierra": {
              "url": "https://homebrew.bintray.com/bottles/reattach-to-user-namespace-2.8.sierra.bottle.tar.gz",
              "sha256": "1ec537d4be63bbcdaf3644506d0b272051fd2617db84c111152a33d8d0184339"
            }
          }
        }
      }
    },
    "cask": {
      "docker": {
        "version": "2.1.0.5,40693",
        "options": {
          "args": {
            "appdir": "/Users/tk/Applications"
          }
        }
      },
      "firefox": {
        "version": "72.0.1",
        "options": {
          "args": {
            "appdir": "/Users/tk/Applications"
          }
        }
      },
      "google-chrome": {
        "version": "79.0.3945.79",
        "options": {
          "args": {
            "appdir": "/Users/tk/Applications"
          }
        }
      },
      "google-cloud-sdk": {
        "version": "latest",
        "options": {
          "args": {
            "appdir": "/Users/tk/Applications"
          }
        }
      },
      "keepassxc": {
        "version": "2.5.3",
        "options": {
          "args": {
            "appdir": "/Users/tk/Applications"
          }
        }
      }
    }
  },
  "system": {
    "macos": {
      "catalina": {
        "HOMEBREW_VERSION": "2.2.4-18-gf8a4dd9",
        "HOMEBREW_PREFIX": "/usr/local",
        "Homebrew/homebrew-core": "84343001e0a5f4fbd601c67d2dc38abdadb3000f",
        "CLT": "11.0.33.16",
        "Xcode": "11.2",
        "macOS": "10.15.2"
      }
    }
  }
}